mypv/__init__.py
mypv/cli.py
mypv/discovery.py
mypv/py.typed
mypv/acthor/__init__.py
mypv/acthor/_acthor.py
mypv/acthor/_features.py
mypv/acthor/_http.py
mypv/acthor/_registers.py
mypv-0.2.0.dist-info/METADATA
mypv-0.2.0.dist-info/WHEEL
mypv-0.2.0.dist-info/entry_points.txt
mypv-0.2.0.dist-info/RECORD
