Metadata-Version: 2.4
Name: mypv
Version: 0.2.0
Summary: my-PV device communication library
Project-URL: Documentation, https://mypv.readthedocs.io
Project-URL: Repository, https://github.com/siku2/home-automation-libraries.git
Project-URL: Issues, https://github.com/siku2/home-automation-libraries/issues
Author-email: Simon Berger <simon@siku2.io>
Maintainer-email: Simon Berger <simon@siku2.io>
License-Expression: MIT
Keywords: acthor,mypv
Requires-Python: >=3.13
Requires-Dist: pymodbus>=3.9.2
Provides-Extra: http
Requires-Dist: httpx>=0.28.1; extra == 'http'
